synth_data_metrics/__init__.py
synth_data_metrics/datasets.py
synth_data_metrics/evaluator.py
synth_data_metrics/plot.py
synth_data_metrics/utils.py
synth_data_metrics/metrics/__init__.py
synth_data_metrics/metrics/image_metrics.py
synth_data_metrics/metrics/ts_metrics.py
synthetic_data_metrics/__init__.py
synthetic_data_metrics/datasets.py
synthetic_data_metrics/evaluator.py
synthetic_data_metrics/plot.py
synthetic_data_metrics/utils.py
synthetic_data_metrics/metrics/__init__.py
synthetic_data_metrics/metrics/image_metrics.py
synthetic_data_metrics/metrics/ts_metrics.py
synthmetricstest/__init__.py
synthmetricstest/to_lower_case.py
synth_data_metrics-0.0.1.dist-info/METADATA
synth_data_metrics-0.0.1.dist-info/WHEEL
synth_data_metrics-0.0.1.dist-info/top_level.txt
synth_data_metrics-0.0.1.dist-info/RECORD
