Metadata-Version: 2.1
Name: synth-data-metrics
Version: 0.0.1
Summary: Synthetic Data Metrics is a Python library for evaluating synthetic data quality across a wide range of data types (image, tabular, time series, language) and approaches to evaluation.
Home-page: https://github.com/NewcastleRSE/synthetic_data_metrics/tree/dev
Author: K.Court
Author-email: kate.court@ncl.ac.uk
Classifier: Programming Language :: Python :: 3.10
Classifier: License :: OSI Approved :: MIT License
Requires-Dist: absl-py (==1.4.0)
Requires-Dist: astunparse (==1.6.4)
Requires-Dist: cachetools (==5.3.0)
Requires-Dist: certifi (==2022.12.7)
Requires-Dist: charset-normalizer (==3.0.1)
Requires-Dist: flatbuffers (==23.1.21)
Requires-Dist: gast (==0.4.0)
Requires-Dist: google-auth (==2.16.0)
Requires-Dist: google-auth-oauthlib (==0.4.6)
Requires-Dist: google-pasta (==0.2.0)
Requires-Dist: grpcio (==1.51.1)
Requires-Dist: h5py (==3.8.0)
Requires-Dist: idna (==3.4)
Requires-Dist: imageio (==2.25.0)
Requires-Dist: joblib (==1.2.0)
Requires-Dist: keras (==2.11.0)
Requires-Dist: libclang (==15.0.6.1)
Requires-Dist: Markdown (==3.4.1)
Requires-Dist: MarkupSafe (==2.1.2)
Requires-Dist: networkx (==3.0)
Requires-Dist: numpy (==1.24.2)
Requires-Dist: oauthlib (==3.2.2)
Requires-Dist: opt-einsum (==3.3.0)
Requires-Dist: packaging (==23.0)
Requires-Dist: pandas (==1.5.3)
Requires-Dist: Pillow (==9.4.0)
Requires-Dist: protobuf (==3.19.6)
Requires-Dist: pyasn1 (==0.4.8)
Requires-Dist: pyasn1-modules (==0.2.8)
Requires-Dist: python-dateutil (==2.8.2)
Requires-Dist: pytz (==2022.7.1)
Requires-Dist: PyWavelets (==1.4.1)
Requires-Dist: requests (==2.28.2)
Requires-Dist: requests-oauthlib (==1.3.1)
Requires-Dist: rsa (==4.9)
Requires-Dist: scikit-image (==0.19.3)
Requires-Dist: scikit-learn (==1.2.1)
Requires-Dist: scipy (==1.10.0)
Requires-Dist: six (==1.16.0)
Requires-Dist: tensorboard (==2.11.2)
Requires-Dist: tensorboard-data-server (==0.6.1)
Requires-Dist: tensorboard-plugin-wit (==1.8.1)
Requires-Dist: tensorflow (==2.11.0)
Requires-Dist: tensorflow-estimator (==2.11.0)
Requires-Dist: tensorflow-io-gcs-filesystem (==0.30.0)
Requires-Dist: termcolor (==2.2.0)
Requires-Dist: threadpoolctl (==3.1.0)
Requires-Dist: tifffile (==2023.2.3)
Requires-Dist: typing-extensions (==4.4.0)
Requires-Dist: urllib3 (==1.26.14)
Requires-Dist: Werkzeug (==2.2.2)
Requires-Dist: wrapt (==1.14.1)
Requires-Dist: matplotlib (==3.6.3)
